jsonAI/__init__.py
jsonAI/api.py
jsonAI/api_server/app.py
jsonAI/api_server/schemas.py
jsonAI/api_server/security.py
jsonAI/async_generation.py
jsonAI/async_jsonformer.py
jsonAI/async_tool_executor.py
jsonAI/cli.py
jsonAI/format.py
jsonAI/logits_processors.py
jsonAI/main.py
jsonAI/mcp_client.py
jsonAI/model_backends.py
jsonAI/output_formatter.py
jsonAI/performance.py
jsonAI/prob_choice_tree.py
jsonAI/schema_generator.py
jsonAI/schema_validator.py
jsonAI/tool_registry.py
jsonAI/type_generator.py
jsonAI/type_prefixes.py
jsonAI/utils/prefix_utils.py
jsonai-0.15.2.4.dist-info/METADATA
jsonai-0.15.2.4.dist-info/WHEEL
jsonai-0.15.2.4.dist-info/RECORD
