Metadata-Version: 2.3
Name: jsonAI
Version: 0.15.2.4
Summary: A Python library for dynamic JSON generation based on schemas using language models.
License: MIT
Keywords: json,llm,schema,generation,fastapi,openai,ollama,transformers
Author: 1rgs
Author-email: kishoretvk9@gmail.com
Requires-Python: >=3.9,<4.0
Classifier: Intended Audience :: Developers
Classifier: License :: OSI Approved :: MIT License
Classifier: Operating System :: OS Independent
Classifier: Programming Language :: Python :: 3
Classifier: Programming Language :: Python :: 3.9
Classifier: Programming Language :: Python :: 3.10
Classifier: Programming Language :: Python :: 3.11
Classifier: Programming Language :: Python :: 3.12
Classifier: Programming Language :: Python :: 3.13
Classifier: Topic :: Software Development :: Libraries :: Application Frameworks
Classifier: Topic :: Software Development :: Libraries :: Python Modules
Requires-Dist: PyYAML (>=6.0.1,<7.0.0)
Requires-Dist: aiohttp (>=3.9.5,<4.0.0)
Requires-Dist: cachetools (>=5.3.1,<6.0.0)
Requires-Dist: click (>=8.1.7,<9.0.0)
Requires-Dist: jaxtyping (>=0.2.28,<0.3.0)
Requires-Dist: jsonschema (>=4.22.0,<5.0.0)
Requires-Dist: lxml (>=5.2.2,<6.0.0)
Requires-Dist: ollama (>=0.2.1,<0.3.0)
Requires-Dist: opentelemetry-api (>=1.24.0,<2.0.0)
Requires-Dist: opentelemetry-exporter-otlp (>=1.24.0,<2.0.0)
Requires-Dist: opentelemetry-instrumentation-asgi (>=0.45b0,<0.46)
Requires-Dist: opentelemetry-instrumentation-fastapi (>=0.45b0,<0.46)
Requires-Dist: opentelemetry-sdk (>=1.24.0,<2.0.0)
Requires-Dist: prometheus-client (>=0.20.0,<0.21.0)
Requires-Dist: requests (>=2.32.0,<3.0.0)
Requires-Dist: termcolor (>=2.3.0,<3.0.0)
Project-URL: Documentation, https://github.com/kishoretvk/GenerativeJson#readme
Project-URL: Homepage, https://github.com/kishoretvk/GenerativeJson
Project-URL: Repository, https://github.com/kishoretvk/GenerativeJson
